LICENSE
MANIFEST.in
README.rst
setup.py
sqlalchemy_pilo.py
sqlalchemy_pilo.egg-info/PKG-INFO
sqlalchemy_pilo.egg-info/SOURCES.txt
sqlalchemy_pilo.egg-info/dependency_links.txt
sqlalchemy_pilo.egg-info/requires.txt
sqlalchemy_pilo.egg-info/top_level.txt