Metadata-Version: 1.1
Name: sqlalchemy-pilo
Version: 0.9.2
Summary: Mongo.
Home-page: https://github.com/bninja/sqlalchemy-pilo/
Author: egon
Author-email: spengler@gb.com
License: Copyright (c) 2014 terrans.
